{"instances":[{"type":"bbox","classId":5,"probability":100,"points":{"x1":451.938232421875,"x2":1459.800048828125,"y1":192.95654296875,"y2":428.8999938964844},"groupId":0,"pointLabels":{},"locked":false,"visible":true,"attributes":[],"className":"Fresh blood"},{"type":"bbox","classId":5,"probability":100,"points":{"x1":406.1283874511719,"x2":1540.300048828125,"y1":430.334716796875,"y2":874.5999755859375},"groupId":0,"pointLabels":{},"locked":false,"visible":true,"attributes":[],"className":"Fresh blood"}],"tags":[],"metadata":{"version":"1.0.0","name":"V00013441.png","status":"Completed"}}