{"instances":[{"type":"bbox","classId":5,"probability":100,"points":{"x1":754.5607299804688,"x2":1425.0999755859375,"y1":54.138885498046875,"y2":1018.9000244140625},"groupId":0,"pointLabels":{},"locked":false,"visible":true,"attributes":[],"className":"Fresh blood"},{"type":"bbox","classId":5,"probability":100,"points":{"x1":370.0357971191406,"x2":668.5,"y1":312.3397216796875,"y2":776},"groupId":0,"pointLabels":{},"locked":false,"visible":true,"attributes":[],"className":"Fresh blood"}],"tags":[],"metadata":{"version":"1.0.0","name":"V00000691.png","status":"Completed"}}